Workbook

Sheet Assumptions
A1: OnSite - forecast assumptions (blue = editable inputs). All amounts AUD, excluding GST.
A3: REVENUE (per park, AUD, ex GST)
A4: Monthly fee | B4: 100 | C4: docs/MODES-AND-PAYMENTS.md; parks.js billing
A5: Fee per answered call | B5: 3 | C5: same
A6: Answered (billable) calls per park per week | B6: 15 | C6: Your assumption
A7: Weeks per month | B7: 4.3333333 | C7: 52 weeks / 12
A8: VARIABLE COST PER ANSWERED CALL
A9: Twilio voice (inbound + ConversationRelay, ~2 min call) | B9: 0.16 | C9: docs/TWILIO.md rates: A$0.01 + A$0.07 per min
A10: Staff-transfer leg (avg) | B10: 0.01 | C10: ~10% of calls x ~1 min x A$0.075
A11: Claude (extraction + replies) | B11: 0.2 | C11: ASSUMED - measure in pilot
A12: SMS (summary, pay link, confirmation, reminders) | B12: 0.2 | C12: ASSUMED ~2 texts x A$0.10
A13: Non-billable calls overhead (spam/abandoned) | B13: 0.03 | C13: ASSUMED
A14: PER-PARK MONTHLY COSTS
A15: Twilio numbers (voice + SMS) | B15: 6 | C15: A$3/month each (docs/TWILIO.md)
A16: Support tools & helpdesk software (per park) | B16: 5 | C16: ASSUMED; support labour is now the hires below
A17: Hosting variable (per park) | B17: 1 | C17: ASSUMED
A18: ONE-OFF / FIXED
A19: Sales cost per new park (non-labour) | B19: 150 | C19: ASSUMED travel, events, demo costs; founder does the selling (in salary)
A20: Onboarding cost per new park (non-labour) | B20: 50 | C20: ASSUMED test calls/SMS; labour is the tech support hire
A21: Technical support hire: monthly cost (fully loaded) | B21: 9000 | C21: ASSUMED ~A$80k salary + super and on-costs
A22: First hire starts in month | B22: 9 | C22: ASSUMED
A23: Second hire when parks at start of month reach | B23: 400 | C23: ASSUMED
A24: Hosting base (always-on container, DB, logs) | B24: 150 | C24: ASSUMED
A25: Marketing fixed (website, ads) | B25: 500 | C25: ASSUMED
A26: Insurance, accounting, legal, software | B26: 1200 | C26: ASSUMED
A27: Founder salary (fully loaded) | B27: 7500 | C27: ASSUMED - set to 0 to see cash profit
A28: Company tax rate | B28: 0.25 | C28: Base-rate entity; losses carried forward
A30: Calls per park per month | B30: =$B$6*$B$7 -> 65
A32: New parks signed per month (growth plan)
A33: Month | B33: 1 | C33: 2 | D33: 3 | E33: 4 | F33: 5 | G33: 6 | H33: 7 | I33: 8 | J33: 9 | K33: 10 | L33: 11 | M33: 12 | N33: 13 | O33: 14 | P33: 15 | Q33: 16 | R33: 17 | S33: 18 | T33: 19 | U33: 20 | V33: 21 | W33: 22 | X33: 23 | Y33: 24
A34: New parks | B34: 2 | C34: 2 | D34: 2 | E34: 2 | F34: 2 | G34: 2 | H34: 12 | I34: 18 | J34: 26 | K34: 34 | L34: 42 | M34: 56 | N34: 30 | O34: 30 | P34: 30 | Q34: 30 | R34: 30 | S34: 30 | T34: 30 | U34: 30 | V34: 30 | W34: 30 | X34: 30 | Y34: 30
A35: Monthly churn (% of parks at start of month) | B35: 0 | C35: 0 | D35: 0 | E35: 0 | F35: 0 | G35: 0 | H35: 0 | I35: 0 | J35: 0 | K35: 0 | L35: 0 | M35: 0 | N35: 0.01 | O35: 0.01 | P35: 0.01 | Q35: 0.01 | R35: 0.01 | S35: 0.01 | T35: 0.01 | U35: 0.01 | V35: 0.01 | W35: 0.01 | X35: 0.01 | Y35: 0.01

Sheet P&L
A1: OnSite - 24-month forecast profit & loss (AUD, ex GST)
A2: Month | B2: M1 | C2: M2 | D2: M3 | E2: M4 | F2: M5 | G2: M6 | H2: M7 | I2: M8 | J2: M9 | K2: M10 | L2: M11 | M2: M12 | N2: M13 | O2: M14 | P2: M15 | Q2: M16 | R2: M17 | S2: M18 | T2: M19 | U2: M20 | V2: M21 | W2: M22 | X2: M23 | Y2: M24 | Z2: Year 1 | AA2: Year 2
A3: New parks signed | B3: =Assumptions!B34 -> 2 | C3: =Assumptions!C34 -> 2 | D3: =Assumptions!D34 -> 2 | E3: =Assumptions!E34 -> 2 | F3: =Assumptions!F34 -> 2 | G3: =Assumptions!G34 -> 2 | H3: =Assumptions!H34 -> 12 | I3: =Assumptions!I34 -> 18 | ... Y3: =Assumptions!Y34 -> 30 | Z3: =SUM(B3:M3) -> 200 | AA3: =SUM(N3:Y3) -> 360
A4: Parks churned | B4: =B5*Assumptions!B35 -> 0 | C4: =C5*Assumptions!C35 -> 0 | D4: =D5*Assumptions!D35 -> 0 | E4: =E5*Assumptions!E35 -> 0 | F4: =F5*Assumptions!F35 -> 0 | G4: =G5*Assumptions!G35 -> 0 | H4: =H5*Assumptions!H35 -> 0 | I4: =I5*Assumptions!I35 -> 0 | ... Y4: =Y5*Assumptions!Y35 -> 4.9305289 | Z4: =SUM(B4:M4) -> 0 | AA4: =SUM(N4:Y4) -> 41.877641
A5: Parks at start | B5: 0 | C5: =B6 -> 2 | D5: =C6 -> 4 | E5: =D6 -> 6 | F5: =E6 -> 8 | G5: =F6 -> 10 | H5: =G6 -> 12 | I5: =H6 -> 24 | J5: =I6 -> 42 | ... Y5: =X6 -> 493.05289 | Z5: =B5 -> 0 | AA5: =N5 -> 200
A6: Parks at end | B6: =B5+B3-B4 -> 2 | C6: =C5+C3-C4 -> 4 | D6: =D5+D3-D4 -> 6 | E6: =E5+E3-E4 -> 8 | F6: =F5+F3-F4 -> 10 | G6: =G5+G3-G4 -> 12 | H6: =H5+H3-H4 -> 24 | I6: =I5+I3-I4 -> 42 | ... Y6: =Y5+Y3-Y4 -> 518.12236 | Z6: =M6 -> 200 | AA6: =Y6 -> 518.12236
A7: Average billed parks | B7: =(B5+B6)/2 -> 1 | C7: =(C5+C6)/2 -> 3 | D7: =(D5+D6)/2 -> 5 | E7: =(E5+E6)/2 -> 7 | F7: =(F5+F6)/2 -> 9 | G7: =(G5+G6)/2 -> 11 | H7: =(H5+H6)/2 -> 18 | I7: =(I5+I6)/2 -> 33 | ... Y7: =(Y5+Y6)/2 -> 505.58762
A8: Answered calls | B8: =B7*Assumptions!$B$30 -> 65 | C8: =C7*Assumptions!$B$30 -> 195 | D8: =D7*Assumptions!$B$30 -> 325 | E8: =E7*Assumptions!$B$30 -> 455 | F8: =F7*Assumptions!$B$30 -> 585 | G8: =G7*Assumptions!$B$30 -> 715 | H8: =H7*Assumptions!$B$30 -> 1170 | I8: =I7*Assumptions!$B$30 -> 2145 | ... Y8: =Y7*Assumptions!$B$30 -> 32863.196 | Z8: =SUM(B8:M8) -> 33930 | AA8: =SUM(N8:Y8) -> 282543.64
A9: REVENUE
A10: Monthly fees | B10: =B7*Assumptions!$B$4 -> 100 | C10: =C7*Assumptions!$B$4 -> 300 | D10: =D7*Assumptions!$B$4 -> 500 | E10: =E7*Assumptions!$B$4 -> 700 | F10: =F7*Assumptions!$B$4 -> 900 | G10: =G7*Assumptions!$B$4 -> 1100 | H10: =H7*Assumptions!$B$4 -> 1800 | I10: =I7*Assumptions!$B$4 -> 3300 | ... Y10: =Y7*Assumptions!$B$4 -> 50558.762 | Z10: =SUM(B10:M10) -> 52200 | AA10: =SUM(N10:Y10) -> 434682.53
A11: Per-call fees | B11: =B8*Assumptions!$B$5 -> 195 | C11: =C8*Assumptions!$B$5 -> 585 | D11: =D8*Assumptions!$B$5 -> 975 | E11: =E8*Assumptions!$B$5 -> 1365 | F11: =F8*Assumptions!$B$5 -> 1755 | G11: =G8*Assumptions!$B$5 -> 2145 | H11: =H8*Assumptions!$B$5 -> 3510 | I11: =I8*Assumptions!$B$5 -> 6435 | ... Y11: =Y8*Assumptions!$B$5 -> 98589.587 | Z11: =SUM(B11:M11) -> 101790 | AA11: =SUM(N11:Y11) -> 847630.93
A12: Total revenue | B12: =B10+B11 -> 295 | C12: =C10+C11 -> 885 | D12: =D10+D11 -> 1475 | E12: =E10+E11 -> 2065 | F12: =F10+F11 -> 2655 | G12: =G10+G11 -> 3245 | H12: =H10+H11 -> 5310 | I12: =I10+I11 -> 9735 | ... Y12: =Y10+Y11 -> 149148.35 | Z12: =SUM(B12:M12) -> 153990 | AA12: =SUM(N12:Y12) -> 1282313.5
A13: COST OF SERVICE
A14: Voice, Claude & SMS (per call) | B14: =B8*(Assumptions!$B$9+Assumptions!$B$10+Assumptions!$B$11+Assumptions!$B$12+Assumptions!$B$13) -> 39 | C14: =C8*(Assumptions!$B$9+Assumptions!$B$10+Assumptions!$B$11+Assumptions!$B$12+Assumptions!$B$13) -> 117 | D14: =D8*(Assumptions!$B$9+Assumptions!$B$10+Assumptions!$B$11+Assumptions!$B$12+Assumptions!$B$13) -> 195 | E14: =E8*(Assumptions!$B$9+Assumptions!$B$10+Assumptions!$B$11+Assumptions!$B$12+Assumptions!$B$13) -> 273 | F14: =F8*(Assumptions!$B$9+Assumptions!$B$10+Assumptions!$B$11+Assumptions!$B$12+Assumptions!$B$13) -> 351 | G14: =G8*(Assumptions!$B$9+Assumptions!$B$10+Assumptions!$B$11+Assumptions!$B$12+Assumptions!$B$13) -> 429 | H14: =H8*(Assumptions!$B$9+Assumptions!$B$10+Assumptions!$B$11+Assumptions!$B$12+Assumptions!$B$13) -> 702 | I14: =I8*(Assumptions!$B$9+Assumptions!$B$10+Assumptions!$B$11+Assumptions!$B$12+Assumptions!$B$13) -> 1287 | ... Y14: =Y8*(Assumptions!$B$9+Assumptions!$B$10+Assumptions!$B$11+Assumptions!$B$12+Assumptions!$B$13) -> 19717.917 | Z14: =SUM(B14:M14) -> 20358 | AA14: =SUM(N14:Y14) -> 169526.19
A15: Twilio numbers | B15: =B7*Assumptions!$B$15 -> 6 | C15: =C7*Assumptions!$B$15 -> 18 | D15: =D7*Assumptions!$B$15 -> 30 | E15: =E7*Assumptions!$B$15 -> 42 | F15: =F7*Assumptions!$B$15 -> 54 | G15: =G7*Assumptions!$B$15 -> 66 | H15: =H7*Assumptions!$B$15 -> 108 | I15: =I7*Assumptions!$B$15 -> 198 | ... Y15: =Y7*Assumptions!$B$15 -> 3033.5257 | Z15: =SUM(B15:M15) -> 3132 | AA15: =SUM(N15:Y15) -> 26080.952
A16: Hosting (variable) | B16: =B7*Assumptions!$B$17 -> 1 | C16: =C7*Assumptions!$B$17 -> 3 | D16: =D7*Assumptions!$B$17 -> 5 | E16: =E7*Assumptions!$B$17 -> 7 | F16: =F7*Assumptions!$B$17 -> 9 | G16: =G7*Assumptions!$B$17 -> 11 | H16: =H7*Assumptions!$B$17 -> 18 | I16: =I7*Assumptions!$B$17 -> 33 | ... Y16: =Y7*Assumptions!$B$17 -> 505.58762 | Z16: =SUM(B16:M16) -> 522 | AA16: =SUM(N16:Y16) -> 4346.8253
A17: Total cost of service | B17: =B14+B15+B16 -> 46 | C17: =C14+C15+C16 -> 138 | D17: =D14+D15+D16 -> 230 | E17: =E14+E15+E16 -> 322 | F17: =F14+F15+F16 -> 414 | G17: =G14+G15+G16 -> 506 | H17: =H14+H15+H16 -> 828 | I17: =I14+I15+I16 -> 1518 | ... Y17: =Y14+Y15+Y16 -> 23257.031 | Z17: =SUM(B17:M17) -> 24012 | AA17: =SUM(N17:Y17) -> 199953.96
A18: Gross profit | B18: =B12-B17 -> 249 | C18: =C12-C17 -> 747 | D18: =D12-D17 -> 1245 | E18: =E12-E17 -> 1743 | F18: =F12-F17 -> 2241 | G18: =G12-G17 -> 2739 | H18: =H12-H17 -> 4482 | I18: =I12-I17 -> 8217 | ... Y18: =Y12-Y17 -> 125891.32 | Z18: =SUM(B18:M18) -> 129978 | AA18: =SUM(N18:Y18) -> 1082359.5
A19: Gross margin % | B19: =B18/B12 -> 0.8440678 | C19: =C18/C12 -> 0.8440678 | D19: =D18/D12 -> 0.8440678 | E19: =E18/E12 -> 0.8440678 | F19: =F18/F12 -> 0.8440678 | G19: =G18/G12 -> 0.8440678 | H19: =H18/H12 -> 0.8440678 | I19: =I18/I12 -> 0.8440678 | ... AA19: =AA18/AA12 -> 0.8440678
A20: OPERATING EXPENSES
A21: Sales & onboarding (non-labour) | B21: =B3*(Assumptions!$B$19+Assumptions!$B$20) -> 400 | C21: =C3*(Assumptions!$B$19+Assumptions!$B$20) -> 400 | D21: =D3*(Assumptions!$B$19+Assumptions!$B$20) -> 400 | E21: =E3*(Assumptions!$B$19+Assumptions!$B$20) -> 400 | F21: =F3*(Assumptions!$B$19+Assumptions!$B$20) -> 400 | G21: =G3*(Assumptions!$B$19+Assumptions!$B$20) -> 400 | H21: =H3*(Assumptions!$B$19+Assumptions!$B$20) -> 2400 | I21: =I3*(Assumptions!$B$19+Assumptions!$B$20) -> 3600 | ... Y21: =Y3*(Assumptions!$B$19+Assumptions!$B$20) -> 6000 | Z21: =SUM(B21:M21) -> 40000 | AA21: =SUM(N21:Y21) -> 72000
A22: Support tools & helpdesk | B22: =B7*Assumptions!$B$16 -> 5 | C22: =C7*Assumptions!$B$16 -> 15 | D22: =D7*Assumptions!$B$16 -> 25 | E22: =E7*Assumptions!$B$16 -> 35 | F22: =F7*Assumptions!$B$16 -> 45 | G22: =G7*Assumptions!$B$16 -> 55 | H22: =H7*Assumptions!$B$16 -> 90 | I22: =I7*Assumptions!$B$16 -> 165 | ... Y22: =Y7*Assumptions!$B$16 -> 2527.9381 | Z22: =SUM(B22:M22) -> 2610 | AA22: =SUM(N22:Y22) -> 21734.126
A23: Technical support staff (count) | B23: =IF(Assumptions!B33>=Assumptions!$B$22,1,0)+IF(AND(Assumptions!B33>=Assumptions!$B$22,B5>=Assumptions!$B$23),1,0) -> 0 | C23: =IF(Assumptions!C33>=Assumptions!$B$22,1,0)+IF(AND(Assumptions!C33>=Assumptions!$B$22,C5>=Assumptions!$B$23),1,0) -> 0 | D23: =IF(Assumptions!D33>=Assumptions!$B$22,1,0)+IF(AND(Assumptions!D33>=Assumptions!$B$22,D5>=Assumptions!$B$23),1,0) -> 0 | E23: =IF(Assumptions!E33>=Assumptions!$B$22,1,0)+IF(AND(Assumptions!E33>=Assumptions!$B$22,E5>=Assumptions!$B$23),1,0) -> 0 | F23: =IF(Assumptions!F33>=Assumptions!$B$22,1,0)+IF(AND(Assumptions!F33>=Assumptions!$B$22,F5>=Assumptions!$B$23),1,0) -> 0 | G23: =IF(Assumptions!G33>=Assumptions!$B$22,1,0)+IF(AND(Assumptions!G33>=Assumptions!$B$22,G5>=Assumptions!$B$23),1,0) -> 0 | H23: =IF(Assumptions!H33>=Assumptions!$B$22,1,0)+IF(AND(Assumptions!H33>=Assumptions!$B$22,H5>=Assumptions!$B$23),1,0) -> 0 | I23: =IF(Assumptions!I33>=Assumptions!$B$22,1,0)+IF(AND(Assumptions!I33>=Assumptions!$B$22,I5>=Assumptions!$B$23),1,0) -> 0 | ... Y23: =IF(Assumptions!Y33>=Assumptions!$B$22,1,0)+IF(AND(Assumptions!Y33>=Assumptions!$B$22,Y5>=Assumptions!$B$23),1,0) -> 2 | Z23: =M23 -> 1 | AA23: =Y23 -> 2
A24: Technical support salaries | B24: =B23*Assumptions!$B$21 -> 0 | C24: =C23*Assumptions!$B$21 -> 0 | D24: =D23*Assumptions!$B$21 -> 0 | E24: =E23*Assumptions!$B$21 -> 0 | F24: =F23*Assumptions!$B$21 -> 0 | G24: =G23*Assumptions!$B$21 -> 0 | H24: =H23*Assumptions!$B$21 -> 0 | I24: =I23*Assumptions!$B$21 -> 0 | ... Y24: =Y23*Assumptions!$B$21 -> 18000 | Z24: =SUM(B24:M24) -> 36000 | AA24: =SUM(N24:Y24) -> 144000
A25: Hosting base | B25: =Assumptions!$B$24 -> 150 | C25: =Assumptions!$B$24 -> 150 | D25: =Assumptions!$B$24 -> 150 | E25: =Assumptions!$B$24 -> 150 | F25: =Assumptions!$B$24 -> 150 | G25: =Assumptions!$B$24 -> 150 | H25: =Assumptions!$B$24 -> 150 | I25: =Assumptions!$B$24 -> 150 | ... Y25: =Assumptions!$B$24 -> 150 | Z25: =SUM(B25:M25) -> 1800 | AA25: =SUM(N25:Y25) -> 1800
A26: Marketing | B26: =Assumptions!$B$25 -> 500 | C26: =Assumptions!$B$25 -> 500 | D26: =Assumptions!$B$25 -> 500 | E26: =Assumptions!$B$25 -> 500 | F26: =Assumptions!$B$25 -> 500 | G26: =Assumptions!$B$25 -> 500 | H26: =Assumptions!$B$25 -> 500 | I26: =Assumptions!$B$25 -> 500 | ... Y26: =Assumptions!$B$25 -> 500 | Z26: =SUM(B26:M26) -> 6000 | AA26: =SUM(N26:Y26) -> 6000
A27: Insurance, accounting, legal | B27: =Assumptions!$B$26 -> 1200 | C27: =Assumptions!$B$26 -> 1200 | D27: =Assumptions!$B$26 -> 1200 | E27: =Assumptions!$B$26 -> 1200 | F27: =Assumptions!$B$26 -> 1200 | G27: =Assumptions!$B$26 -> 1200 | H27: =Assumptions!$B$26 -> 1200 | I27: =Assumptions!$B$26 -> 1200 | ... Y27: =Assumptions!$B$26 -> 1200 | Z27: =SUM(B27:M27) -> 14400 | AA27: =SUM(N27:Y27) -> 14400
A28: Founder salary | B28: =Assumptions!$B$27 -> 7500 | C28: =Assumptions!$B$27 -> 7500 | D28: =Assumptions!$B$27 -> 7500 | E28: =Assumptions!$B$27 -> 7500 | F28: =Assumptions!$B$27 -> 7500 | G28: =Assumptions!$B$27 -> 7500 | H28: =Assumptions!$B$27 -> 7500 | I28: =Assumptions!$B$27 -> 7500 | ... Y28: =Assumptions!$B$27 -> 7500 | Z28: =SUM(B28:M28) -> 90000 | AA28: =SUM(N28:Y28) -> 90000
A29: Total operating expenses | B29: =SUM(B21:B28) -> 9755 | C29: =SUM(C21:C28) -> 9765 | D29: =SUM(D21:D28) -> 9775 | E29: =SUM(E21:E28) -> 9785 | F29: =SUM(F21:F28) -> 9795 | G29: =SUM(G21:G28) -> 9805 | H29: =SUM(H21:H28) -> 11840 | I29: =SUM(I21:I28) -> 13115 | ... Y29: =SUM(Y21:Y28) -> 35879.938 | Z29: =SUM(B29:M29) -> 190814 | AA29: =SUM(N29:Y29) -> 349950.13
A30: EBITDA / profit before tax | B30: =B18-B29 -> -9506 | C30: =C18-C29 -> -9018 | D30: =D18-D29 -> -8530 | E30: =E18-E29 -> -8042 | F30: =F18-F29 -> -7554 | G30: =G18-G29 -> -7066 | H30: =H18-H29 -> -7358 | I30: =I18-I29 -> -4898 | ... Y30: =Y18-Y29 -> 90011.38 | Z30: =SUM(B30:M30) -> -60836 | AA30: =SUM(N30:Y30) -> 732409.36
A31: Income tax | B31: =MAX(0,Assumptions!$B$28*MAX(0,SUM($B30:B30))-0) -> 0 | C31: =MAX(0,Assumptions!$B$28*MAX(0,SUM($B30:C30))-SUM($B31:B31)) -> 0 | D31: =MAX(0,Assumptions!$B$28*MAX(0,SUM($B30:D30))-SUM($B31:C31)) -> 0 | E31: =MAX(0,Assumptions!$B$28*MAX(0,SUM($B30:E30))-SUM($B31:D31)) -> 0 | F31: =MAX(0,Assumptions!$B$28*MAX(0,SUM($B30:F30))-SUM($B31:E31)) -> 0 | G31: =MAX(0,Assumptions!$B$28*MAX(0,SUM($B30:G30))-SUM($B31:F31)) -> 0 | H31: =MAX(0,Assumptions!$B$28*MAX(0,SUM($B30:H30))-SUM($B31:G31)) -> 0 | I31: =MAX(0,Assumptions!$B$28*MAX(0,SUM($B30:I30))-SUM($B31:H31)) -> 0 | J31: =MAX(0,Assumptions!$B$28*MAX(0,SUM($B30:J30))-SUM($B31:I31)) -> 0 | ... Y31: =MAX(0,Assumptions!$B$28*MAX(0,SUM($B30:Y30))-SUM($B31:X31)) -> 22502.845 | Z31: =SUM(B31:M31) -> 0 | AA31: =SUM(N31:Y31) -> 167893.34
A32: Net profit | B32: =B30-B31 -> -9506 | C32: =C30-C31 -> -9018 | D32: =D30-D31 -> -8530 | E32: =E30-E31 -> -8042 | F32: =F30-F31 -> -7554 | G32: =G30-G31 -> -7066 | H32: =H30-H31 -> -7358 | I32: =I30-I31 -> -4898 | ... Y32: =Y30-Y31 -> 67508.535 | Z32: =SUM(B32:M32) -> -60836 | AA32: =SUM(N32:Y32) -> 564516.02
A33: Cumulative net profit | B33: =SUM($B32:B32) -> -9506 | C33: =SUM($B32:C32) -> -18524 | D33: =SUM($B32:D32) -> -27054 | E33: =SUM($B32:E32) -> -35096 | F33: =SUM($B32:F32) -> -42650 | G33: =SUM($B32:G32) -> -49716 | H33: =SUM($B32:H32) -> -57074 | I33: =SUM($B32:I32) -> -61972 | ... Y33: =SUM($B32:Y32) -> 503680.02 | Z33: =M33 -> -60836 | AA33: =Y33 -> 503680.02
